alpha/__init__.py
alpha/alpha.py
alpha/asp.py
alpha/control.py
alpha/log.py
alpha/log_viz.py
alpha/loops.py
alpha/protocol.py
alpha/vehicle_interface.py
alpha_dbw-1.0.dist-info/DESCRIPTION.rst
alpha_dbw-1.0.dist-info/METADATA
alpha_dbw-1.0.dist-info/RECORD
alpha_dbw-1.0.dist-info/WHEEL
alpha_dbw-1.0.dist-info/metadata.json
alpha_dbw-1.0.dist-info/top_level.txt
