Metadata-Version: 2.0
Name: alpha-dbw
Version: 1.0
Summary: Python API to Alpha | OSCAR Project
Home-page: https://gitlab.com/starline/alpha_py
Author: Nikolay Dema
Author-email: ndema2301@gmail.com
License: UNKNOWN
Keywords: alpha,vehicle,api,oscar,drive-by-wire
Platform: UNKNOWN
Classifier: Programming Language :: Python :: 2
Classifier: Programming Language :: Python :: 3
Classifier: License :: OSI Approved :: Apache Software License
Classifier: Operating System :: OS Independent
Requires-Python: >=2.6
Requires-Dist: pyserial (>=3.4)
